dotty_dict/__init__.py
dotty_dict/dotty_dict.py
qmk_dotty_dict-1.3.0.post1.dist-info/AUTHORS.rst
qmk_dotty_dict-1.3.0.post1.dist-info/LICENSE
qmk_dotty_dict-1.3.0.post1.dist-info/METADATA
qmk_dotty_dict-1.3.0.post1.dist-info/WHEEL
qmk_dotty_dict-1.3.0.post1.dist-info/top_level.txt
qmk_dotty_dict-1.3.0.post1.dist-info/RECORD
