Metadata-Version: 2.1
Name: qmk-dotty-dict
Version: 1.3.0.post1
Summary: Dictionary wrapper for quick access to deeply nested keys.
Home-page: https://github.com/pawelzny/dotty_dict
Author: Pawel Zadrozny @pawelzny
Author-email: pawel.zny@gmail.com
License: MIT license
Keywords: dot notation dict wrapper helper utils lib
Platform: UNKNOWN
Classifier: Development Status :: 5 - Production/Stable
Classifier: Intended Audience :: Developers
Classifier: Natural Language :: English
Classifier: Topic :: Software Development
Classifier: Topic :: Software Development :: Libraries :: Python Modules
Classifier: Programming Language :: Python :: 3 :: Only
Classifier: Programming Language :: Python :: 3.5
Classifier: Programming Language :: Python :: 3.6
Classifier: Programming Language :: Python :: 3.7
Classifier: Programming Language :: Python :: 3.8
Classifier: Programming Language :: Python :: Implementation :: CPython
Classifier: Programming Language :: Python :: Implementation :: PyPy
Classifier: License :: OSI Approved :: MIT License
